mintc/__init__.py
mintc/commands.py
mintc/connection.py
mintc/logger.py
mintc/parsers.py
mintc-0.0.4.dist-info/LICENSE
mintc-0.0.4.dist-info/METADATA
mintc-0.0.4.dist-info/WHEEL
mintc-0.0.4.dist-info/top_level.txt
mintc-0.0.4.dist-info/RECORD
