Metadata-Version: 2.1
Name: mintc
Version: 0.0.4
Summary: Minimalistic asyncio-based Tor Controller
Home-page: https://github.com/amateur80lvl/mintc
Author: amateur80lvl
Author-email: amateur80lvl@gmail.com
Keywords: tor,onion,controller,asyncio
Classifier: Development Status :: 3 - Alpha
Classifier: Intended Audience :: Developers
Classifier: Programming Language :: Python
Classifier: Operating System :: OS Independent
Classifier: License :: OSI Approved :: GNU Lesser General Public License v3 (LGPLv3)
Classifier: Topic :: Security
Classifier: Topic :: Software Development :: Libraries :: Python Modules
License-File: LICENSE
